jupyterlab_jitsi/__init__.py
jupyterlab_jitsi/_version.py
jupyterlab_jitsi/handlers.py
jupyterlab_jitsi/jitsi/index.html
jupyterlab_jitsi/labextension/package.json
jupyterlab_jitsi/labextension/schemas/jupyterlab-jitsi/package.json.orig
jupyterlab_jitsi/labextension/schemas/jupyterlab-jitsi/plugin.json
jupyterlab_jitsi/labextension/static/480.1f04dc2d670d49bffbce.js
jupyterlab_jitsi/labextension/static/534.c60355eb2b0db0e0ff41.js
jupyterlab_jitsi/labextension/static/remoteEntry.c042969f69fd94bad12a.js
jupyterlab_jitsi/labextension/static/style.js
jupyterlab_jitsi-0.2.1.data/data/etc/jupyter/jupyter_notebook_config.d/jupyterlab-jitsi.json
jupyterlab_jitsi-0.2.1.data/data/etc/jupyter/jupyter_server_config.d/jupyterlab-jitsi.json
jupyterlab_jitsi-0.2.1.data/data/share/jupyter/labextensions/jupyterlab-jitsi/install.json
jupyterlab_jitsi-0.2.1.data/data/share/jupyter/labextensions/jupyterlab-jitsi/package.json
jupyterlab_jitsi-0.2.1.data/data/share/jupyter/labextensions/jupyterlab-jitsi/schemas/jupyterlab-jitsi/package.json.orig
jupyterlab_jitsi-0.2.1.data/data/share/jupyter/labextensions/jupyterlab-jitsi/schemas/jupyterlab-jitsi/plugin.json
jupyterlab_jitsi-0.2.1.data/data/share/jupyter/labextensions/jupyterlab-jitsi/static/480.1f04dc2d670d49bffbce.js
jupyterlab_jitsi-0.2.1.data/data/share/jupyter/labextensions/jupyterlab-jitsi/static/534.c60355eb2b0db0e0ff41.js
jupyterlab_jitsi-0.2.1.data/data/share/jupyter/labextensions/jupyterlab-jitsi/static/remoteEntry.c042969f69fd94bad12a.js
jupyterlab_jitsi-0.2.1.data/data/share/jupyter/labextensions/jupyterlab-jitsi/static/style.js
jupyterlab_jitsi-0.2.1.dist-info/LICENSE
jupyterlab_jitsi-0.2.1.dist-info/METADATA
jupyterlab_jitsi-0.2.1.dist-info/WHEEL
jupyterlab_jitsi-0.2.1.dist-info/top_level.txt
jupyterlab_jitsi-0.2.1.dist-info/RECORD
